ordinalizer/__init__.py
ordinalizer/ordinalizer.py
ordinalizer/tests/__init__.py
ordinalizer/tests/test_ordinalizer.py
ordinalizer-1.0.0.dist-info/DESCRIPTION.rst
ordinalizer-1.0.0.dist-info/METADATA
ordinalizer-1.0.0.dist-info/RECORD
ordinalizer-1.0.0.dist-info/WHEEL
ordinalizer-1.0.0.dist-info/metadata.json
ordinalizer-1.0.0.dist-info/top_level.txt
