Metadata-Version: 2.0
Name: ordinalizer
Version: 1.0.0
Summary: A package helping to get numbers as ordinals
Home-page: https://github.com/sandordargo/ordinalizer
Author: Sandor DARGO
Author-email: sandor.dargo@gmail.com
License: UNKNOWN
Platform: UNKNOWN
Classifier: Programming Language :: Python :: 3
Classifier: License :: OSI Approved :: MIT License
Classifier: Operating System :: OS Independent
